{
  "project_info": {
    "project_number": "490471891056",
    "firebase_url": "https://theviralpages-7f0a3.firebaseio.com",
    "project_id": "theviralpages-7f0a3",
    "storage_bucket": "theviralpages-7f0a3.appspot.com"
  },
  "client": [
    {
      "client_info": {
        "mobilesdk_app_id": "1:490471891056:android:20173e0bd2687e40",
        "android_client_info": {
          "package_name": "com.theviralpages.hindi"
        }
      },
      "oauth_client": [
        {
          "client_id": "490471891056-l9l81qirtngp975pdp14mg3euqckgh5g.apps.googleusercontent.com",
          "client_type": 3
        }
      ],
      "api_key": [
        {
          "current_key": "AIzaSyD13wJdlSEDxEZiegrNU3AyAL-mavI2axY"
        }
      ],
      "services": {
        "analytics_service": {
          "status": 1
        },
        "appinvite_service": {
          "status": 1,
          "other_platform_oauth_client": []
        },
        "ads_service": {
          "status": 2
        }
      }
    }
  ],
  "configuration_version": "1"
}